README.md
setup.cfg
setup.py
payeer_pyapi/__init__.py
payeer_pyapi/api.py
payeer_pyapi/exceptions.py
payeer_pyapi.egg-info/PKG-INFO
payeer_pyapi.egg-info/SOURCES.txt
payeer_pyapi.egg-info/dependency_links.txt
payeer_pyapi.egg-info/requires.txt
payeer_pyapi.egg-info/top_level.txt