Metadata-Version: 2.1
Name: payeer-pyapi
Version: 1.0.0
Summary: Connecting the Payeer payment system to your product
Home-page: https://github.com/St0rm1k/payeer_pyapi
Author: Mr Storm
Author-email: medikk19@mail.ru
License: UNKNOWN
Project-URL: GitHub, https://github.com/St0rm1k/payeer_pyapi
Project-URL: Guide, https://github.com/St0rm1k/payeer_pyapi/blob/main/README.md
Project-URL: Bug Tracker, https://github.com/St0rm1k/payeer_pyapi/issues
Platform: UNKNOWN
Classifier: Programming Language :: Python :: 3
Classifier: License :: OSI Approved :: MIT License
Classifier: Operating System :: OS Independent
Requires-Python: >=3.7
